thonnycontrib/thonny-subway-surfers.py
thonny_subway_surfers-1.0.0.dist-info/LICENSE
thonny_subway_surfers-1.0.0.dist-info/METADATA
thonny_subway_surfers-1.0.0.dist-info/WHEEL
thonny_subway_surfers-1.0.0.dist-info/top_level.txt
thonny_subway_surfers-1.0.0.dist-info/RECORD
