Metadata-Version: 2.1
Name: thonny-subway-surfers
Version: 1.0.0
Summary: This plugin seamlessly integrates Subway Surfers gameplay into your Thonny IDE.
Author: McBigBob
Project-URL: Source, https://github.com/McBigBob/thonny-subway-surfers
Keywords: subway surfers,thonny,bored,gameplay,plugin
Classifier: Development Status :: 3 - Alpha
Classifier: Intended Audience :: Developers
Classifier: Topic :: Software Development :: Build Tools
Classifier: License :: OSI Approved :: MIT License
Classifier: Programming Language :: Python :: 3
Classifier: Programming Language :: Python :: 3.7
Classifier: Programming Language :: Python :: 3.8
Classifier: Programming Language :: Python :: 3.9
Classifier: Programming Language :: Python :: 3.10
Classifier: Programming Language :: Python :: 3.11
Classifier: Programming Language :: Python :: 3 :: Only
Requires-Python: >=3.7
License-File: LICENSE
Requires-Dist: thonny
Requires-Dist: pillow
